sturdy/__init__.py
sturdy/command.py
sturdy/extras/__init__.py
sturdy/extras/empty_command.py
sturdy/extras/plugin_system.py
sturdy/extras/processor.py
sturdy/extras/scope_based_ioc.py
sturdy/extras/scope_context_manager.py
sturdy/ioc.py
sturdy-0.2.2.dist-info/METADATA
sturdy-0.2.2.dist-info/WHEEL
sturdy-0.2.2.dist-info/entry_points.txt
sturdy-0.2.2.dist-info/RECORD
