Metadata-Version: 2.1
Name: sturdy
Version: 0.2.2
Summary: Modular app server
Home-page: https://github.com/zaryanezrya/sturdy
License: MIT
Keywords: Plugin,IoC,Inversion of control,resolve
Author: Ivan Sharun
Author-email: ivan@sha.run
Requires-Python: >=3.7,<4.0
Classifier: License :: OSI Approved :: MIT License
Classifier: Programming Language :: Python :: 3
Classifier: Programming Language :: Python :: 3.7
Classifier: Programming Language :: Python :: 3.8
Classifier: Programming Language :: Python :: 3.9
Classifier: Programming Language :: Python :: 3.10
Classifier: Programming Language :: Python :: 3.11
Classifier: Programming Language :: Python :: 3.12
Project-URL: Repository, https://github.com/zaryanezrya/sturdy
